backstagetasks/__init__.py
backstagetasks/__main__.py
backstagetasks/.pyrustic/backstage/build_report.json
backstagetasks/cli/__init__.py
backstagetasks/cli/build.py
backstagetasks/cli/init.py
backstagetasks/cli/release.py
backstagetasks/cli/run.py
backstagetasks/cli/setup.py
backstagetasks/cli/version.py
backstagetasks/core/__init__.py
backstagetasks/core/building.py
backstagetasks/core/funcs.py
backstagetasks/core/lite_test_runner.py
backstagetasks/core/pymisc.py
backstagetasks/core/releaser.py
backstagetasks/core/tasks.py
backstagetasks/error/__init__.py
backstagetasks/script/__init__.py
backstagetasks/script/build_project.py
backstagetasks/script/init_project.py
backstagetasks/script/pypi_release.py
backstagetasks/script/update_version.py
backstagetasks/template/app/changelog_template.txt
backstagetasks/template/app/gitignore_template.txt
backstagetasks/template/app/latest_release_template.txt
backstagetasks/template/app/main_template.txt
backstagetasks/template/app/manifest_template.txt
backstagetasks/template/app/module_template.txt
backstagetasks/template/app/pyproject_template.txt
backstagetasks/template/app/readme_template.txt
backstagetasks/template/app/setup_cfg_template.txt
backstagetasks/template/app/setup_py_template.txt
backstagetasks/template/app/test_template.txt
backstagetasks/template/app/tests_main_template.txt
backstagetasks/template/app/version_template.txt
backstagetasks/template/tasks/build.txt
backstagetasks/template/tasks/init.txt
backstagetasks/template/tasks/release.txt
tests/__init__.py
tests/__main__.py
backstagetasks-0.0.4.dist-info/METADATA
backstagetasks-0.0.4.dist-info/WHEEL
backstagetasks-0.0.4.dist-info/entry_points.txt
backstagetasks-0.0.4.dist-info/top_level.txt
backstagetasks-0.0.4.dist-info/RECORD
