Metadata-Version: 2.1
Name: backstagetasks
Version: 0.0.4
Summary: Backstage Tasks
Home-page: https://pyrustic.github.com
Author: Pyrustic Evangelist
Author-email: rusticalex@yahoo.com
Maintainer: Pyrustic Evangelist
Maintainer-email: rusticalex@yahoo.com
License: MIT
Keywords: application
Platform: UNKNOWN
Classifier: Programming Language :: Python :: 3
Classifier: License :: OSI Approved :: MIT License
Classifier: Operating System :: OS Independent
Requires-Python: >=3.5
Requires-Dist: setuptools
Requires-Dist: wheel
Requires-Dist: importlib-metadata ; python_version < "3.8"
